README
setup.py
TracShellExampleMacro.egg-info/PKG-INFO
TracShellExampleMacro.egg-info/SOURCES.txt
TracShellExampleMacro.egg-info/dependency_links.txt
TracShellExampleMacro.egg-info/entry_points.txt
TracShellExampleMacro.egg-info/requires.txt
TracShellExampleMacro.egg-info/top_level.txt
shellexample/__init__.py
shellexample/macro.py
