Metadata-Version: 1.0
Name: TracShellExampleMacro
Version: 1.0
Summary: UNKNOWN
Home-page: http://trac-hacks.org/wiki/ShellExampleMacro
Author: moo
Author-email: UNKNOWN
License: BSD
Download-URL: http://trac-hacks.org/svn/exampleshellmacro/0.11#egg=TracShellExampleMacro-dev
Keywords: trac plugin macro
Platform: UNKNOWN
Classifier: Framework :: Trac
Classifier: Development Status :: 1 - Planning
Classifier: Environment :: Web Environment
Classifier: License :: OSI Approved :: BSD License
Classifier: Natural Language :: English
Classifier: Operating System :: OS Independent
Classifier: Programming Language :: Python
